<annotation>
	<folder></folder>
	<filename>0093_png.rf.3442132a64fe8691ae392bf13400130a.jpg</filename>
	<path>0093_png.rf.3442132a64fe8691ae392bf13400130a.jpg</path>
	<source>
		<database>roboflow.ai</database>
	</source>
	<size>
		<width>416</width>
		<height>416</height>
		<depth>3</depth>
	</size>
	<segmented>0</segmented>
	<object>
		<name>Stairs</name>
		<pose>Unspecified</pose>
		<truncated>0</truncated>
		<difficult>0</difficult>
		<occluded>0</occluded>
		<bndbox>
			<xmin>1</xmin>
			<xmax>35</xmax>
			<ymin>155</ymin>
			<ymax>226</ymax>
		</bndbox>
		<polygon>
			<x1>0</x1>
			<y1>225.010299</y1>
			<x2>34.104067</x2>
			<y2>188.754188</y2>
			<x3>27.049631</x3>
			<y3>169.013058</y3>
			<x4>0</x4>
			<y4>154.266771</y4>
			<x5>0</x5>
			<y5>225.010299</y5>
		</polygon>
	</object>
	<object>
		<name>Stairs</name>
		<pose>Unspecified</pose>
		<truncated>0</truncated>
		<difficult>0</difficult>
		<occluded>0</occluded>
		<bndbox>
			<xmin>106</xmin>
			<xmax>188</xmax>
			<ymin>158</ymin>
			<ymax>417</ymax>
		</bndbox>
		<polygon>
			<x1>141.997163</x1>
			<y1>156.794595</y1>
			<x2>104.997692</x2>
			<y2>184.990186</y2>
			<x3>115.089127</x3>
			<y3>398.10645</y3>
			<x4>128.017982</x4>
			<y4>415.750569</y4>
			<x5>186.550715</x5>
			<y5>368.274369</y5>
			<x6>151.728424</x6>
			<y6>175.868318</y6>
			<x7>141.997163</x7>
			<y7>156.794595</y7>
		</polygon>
	</object>
	<object>
		<name>Stairs</name>
		<pose>Unspecified</pose>
		<truncated>0</truncated>
		<difficult>0</difficult>
		<occluded>0</occluded>
		<bndbox>
			<xmin>194</xmin>
			<xmax>380</xmax>
			<ymin>144</ymin>
			<ymax>331</ymax>
		</bndbox>
		<polygon>
			<x1>223.265475</x1>
			<y1>143.488011</y1>
			<x2>193.275991</x2>
			<y2>176.891698</y2>
			<x3>197.551612</x3>
			<y3>204.281547</y3>
			<x4>348.94388</x4>
			<y4>329.682265</y4>
			<x5>378.668001</x5>
			<y5>279.271211</y5>
			<x6>376.562124</x6>
			<y6>249.443325</y6>
			<x7>223.265475</x7>
			<y7>143.488011</y7>
		</polygon>
	</object>
</annotation>
