<annotation>
	<folder></folder>
	<filename>0112_png.rf.d70bf7276ab9f72c0ba028d69ffe0eb1.jpg</filename>
	<path>0112_png.rf.d70bf7276ab9f72c0ba028d69ffe0eb1.jpg</path>
	<source>
		<database>roboflow.ai</database>
	</source>
	<size>
		<width>416</width>
		<height>416</height>
		<depth>3</depth>
	</size>
	<segmented>0</segmented>
	<object>
		<name>Stairs</name>
		<pose>Unspecified</pose>
		<truncated>0</truncated>
		<difficult>0</difficult>
		<occluded>0</occluded>
		<bndbox>
			<xmin>3</xmin>
			<xmax>32</xmax>
			<ymin>33</ymin>
			<ymax>95</ymax>
		</bndbox>
		<polygon>
			<x1>31.480136</x1>
			<y1>77.078135</y1>
			<x2>25.071456</x2>
			<y2>50.817037</y2>
			<x3>3.174039</x3>
			<y3>31.839805</y3>
			<x4>2.614978</x4>
			<y4>56.372844</y4>
			<x5>1.950305</x5>
			<y5>94.45191</y5>
			<x6>31.480136</x6>
			<y6>77.078135</y6>
		</polygon>
	</object>
	<object>
		<name>Stairs</name>
		<pose>Unspecified</pose>
		<truncated>0</truncated>
		<difficult>0</difficult>
		<occluded>0</occluded>
		<bndbox>
			<xmin>58</xmin>
			<xmax>150</xmax>
			<ymin>70</ymin>
			<ymax>321</ymax>
		</bndbox>
		<polygon>
			<x1>141.819046</x1>
			<y1>69.125508</y1>
			<x2>100.298868</x2>
			<y2>89.320158</y2>
			<x3>56.832921</x3>
			<y3>291.944388</y3>
			<x4>63.864987</x4>
			<y4>319.95965</y4>
			<x5>135.748521</x5>
			<y5>285.767642</y5>
			<x6>148.962652</x6>
			<y6>90.750682</y6>
			<x7>141.819046</x7>
			<y7>69.125508</y7>
		</polygon>
	</object>
	<object>
		<name>Stairs</name>
		<pose>Unspecified</pose>
		<truncated>0</truncated>
		<difficult>0</difficult>
		<occluded>0</occluded>
		<bndbox>
			<xmin>190</xmin>
			<xmax>351</xmax>
			<ymin>78</ymin>
			<ymax>283</ymax>
		</bndbox>
		<polygon>
			<x1>226.375554</x1>
			<y1>76.993482</y1>
			<x2>189.42633</x2>
			<y2>99.0112</y2>
			<x3>189.584676</x3>
			<y3>124.001011</y3>
			<x4>302.25402</x4>
			<y4>282.281971</y4>
			<x5>345.471432</x5>
			<y5>241.778654</y5>
			<x6>350.258597</x6>
			<y6>211.064228</y6>
			<x7>226.375554</x7>
			<y7>76.993482</y7>
		</polygon>
	</object>
</annotation>
