<annotation>
	<folder></folder>
	<filename>0124_png.rf.084b9e4cb3017913a3f6c5a56e956a29.jpg</filename>
	<path>0124_png.rf.084b9e4cb3017913a3f6c5a56e956a29.jpg</path>
	<source>
		<database>roboflow.ai</database>
	</source>
	<size>
		<width>416</width>
		<height>416</height>
		<depth>3</depth>
	</size>
	<segmented>0</segmented>
	<object>
		<name>Stairs</name>
		<pose>Unspecified</pose>
		<truncated>0</truncated>
		<difficult>0</difficult>
		<occluded>0</occluded>
		<bndbox>
			<xmin>23</xmin>
			<xmax>139</xmax>
			<ymin>68</ymin>
			<ymax>353</ymax>
		</bndbox>
		<polygon>
			<x1>133.143451</x1>
			<y1>66.645187</y1>
			<x2>82.42369</x2>
			<y2>85.976157</y2>
			<x3>21.725075</x3>
			<y3>327.118183</y3>
			<x4>33.137927</x4>
			<y4>351.537809</y4>
			<x5>111.962991</x5>
			<y5>320.242005</y5>
			<x6>137.905756</x6>
			<y6>87.051425</y6>
			<x7>133.143451</x7>
			<y7>66.645187</y7>
		</polygon>
	</object>
	<object>
		<name>Stairs</name>
		<pose>Unspecified</pose>
		<truncated>0</truncated>
		<difficult>0</difficult>
		<occluded>0</occluded>
		<bndbox>
			<xmin>184</xmin>
			<xmax>371</xmax>
			<ymin>78</ymin>
			<ymax>319</ymax>
		</bndbox>
		<polygon>
			<x1>223.139799</x1>
			<y1>77.469774</y1>
			<x2>183.235816</x2>
			<y2>100.421613</y2>
			<x3>183.200769</x3>
			<y3>126.073702</y3>
			<x4>313.790815</x4>
			<y4>317.992389</y4>
			<x5>361.575377</x5>
			<y5>263.691551</y5>
			<x6>369.566709</x6>
			<y6>242.121278</y6>
			<x7>223.139799</x7>
			<y7>77.469774</y7>
		</polygon>
	</object>
</annotation>
