<annotation>
	<folder></folder>
	<filename>0127_png.rf.f3c77d03a4a7f0e8cf1f2da2b7d73713.jpg</filename>
	<path>0127_png.rf.f3c77d03a4a7f0e8cf1f2da2b7d73713.jpg</path>
	<source>
		<database>roboflow.ai</database>
	</source>
	<size>
		<width>416</width>
		<height>416</height>
		<depth>3</depth>
	</size>
	<segmented>0</segmented>
	<object>
		<name>Stairs</name>
		<pose>Unspecified</pose>
		<truncated>0</truncated>
		<difficult>0</difficult>
		<occluded>0</occluded>
		<bndbox>
			<xmin>1</xmin>
			<xmax>152</xmax>
			<ymin>36</ymin>
			<ymax>317</ymax>
		</bndbox>
		<polygon>
			<x1>0</x1>
			<y1>315.72178</y1>
			<x2>84.707371</x2>
			<y2>294.294578</y2>
			<x3>150.276536</x3>
			<y3>57.867713</y3>
			<x4>151.199819</x4>
			<y4>34.653302</y4>
			<x5>94.094329</x5>
			<y5>47.876705</y5>
			<x6>0</x6>
			<y6>257.745492</y6>
			<x7>0</x7>
			<y7>315.72178</y7>
		</polygon>
	</object>
	<object>
		<name>Stairs</name>
		<pose>Unspecified</pose>
		<truncated>0</truncated>
		<difficult>0</difficult>
		<occluded>0</occluded>
		<bndbox>
			<xmin>193</xmin>
			<xmax>369</xmax>
			<ymin>68</ymin>
			<ymax>337</ymax>
		</bndbox>
		<polygon>
			<x1>246.157474</x1>
			<y1>66.542505</y1>
			<x2>196.624235</x2>
			<y2>82.025737</y2>
			<x3>192.448353</x3>
			<y3>106.499675</y3>
			<x4>290.246885</x4>
			<y4>336.032462</y4>
			<x5>353.651677</x5>
			<y5>291.633209</y5>
			<x6>368.119685</x6>
			<y6>259.592486</y6>
			<x7>246.157474</x7>
			<y7>66.542505</y7>
		</polygon>
	</object>
</annotation>
