<annotation>
	<folder></folder>
	<filename>0135_png.rf.4ed8a17819e85491375d26348c81abb3.jpg</filename>
	<path>0135_png.rf.4ed8a17819e85491375d26348c81abb3.jpg</path>
	<source>
		<database>roboflow.ai</database>
	</source>
	<size>
		<width>416</width>
		<height>416</height>
		<depth>3</depth>
	</size>
	<segmented>0</segmented>
	<object>
		<name>Stairs</name>
		<pose>Unspecified</pose>
		<truncated>0</truncated>
		<difficult>0</difficult>
		<occluded>0</occluded>
		<bndbox>
			<xmin>8</xmin>
			<xmax>39</xmax>
			<ymin>1</ymin>
			<ymax>65</ymax>
		</bndbox>
		<polygon>
			<x1>10.61537</x1>
			<y1>0</y1>
			<x2>7.235691</x2>
			<y2>64.48812</y2>
			<x3>38.368718</x3>
			<y3>46.720366</y3>
			<x4>30.554049</x4>
			<y4>19.245475</y4>
			<x5>13.460554</x5>
			<y5>0</y5>
			<x6>10.61537</x6>
			<y6>0</y6>
		</polygon>
	</object>
	<object>
		<name>Stairs</name>
		<pose>Unspecified</pose>
		<truncated>0</truncated>
		<difficult>0</difficult>
		<occluded>0</occluded>
		<bndbox>
			<xmin>40</xmin>
			<xmax>163</xmax>
			<ymin>42</ymin>
			<ymax>331</ymax>
		</bndbox>
		<polygon>
			<x1>156.32666</x1>
			<y1>41.13474</y1>
			<x2>105.865153</x2>
			<y2>64.967129</y2>
			<x3>39.257698</x3>
			<y3>300.945807</y3>
			<x4>51.95509</x4>
			<y4>329.853343</y4>
			<x5>131.321169</x5>
			<y5>297.533371</y5>
			<x6>162.049283</x6>
			<y6>64.381352</y6>
			<x7>156.32666</x7>
			<y7>41.13474</y7>
		</polygon>
	</object>
	<object>
		<name>Stairs</name>
		<pose>Unspecified</pose>
		<truncated>0</truncated>
		<difficult>0</difficult>
		<occluded>0</occluded>
		<bndbox>
			<xmin>205</xmin>
			<xmax>395</xmax>
			<ymin>56</ymin>
			<ymax>313</ymax>
		</bndbox>
		<polygon>
			<x1>249.476039</x1>
			<y1>54.842147</y1>
			<x2>206.169641</x2>
			<y2>80.226272</y2>
			<x3>203.559636</x3>
			<y3>104.80132</y3>
			<x4>329.53411</x4>
			<y4>312.03991</y4>
			<x5>383.813891</x5>
			<y5>260.165534</y5>
			<x6>393.530316</x6>
			<y6>232.432657</y6>
			<x7>249.476039</x7>
			<y7>54.842147</y7>
		</polygon>
	</object>
</annotation>
